cacheplus/__init__.py
cacheplus/__version__.py
cacheplus/_core.py
cacheplus/_hashing.py
cacheplus/_util.py
cacheplus/exceptions.py
cacheplus/factories.py
cacheplus/ref.py
cacheplus/value.py
cacheplus/storage/__init__.py
cacheplus/storage/base.py
cacheplus/storage/file.py
cacheplus/storage/memory.py
cacheplus/storage/mongo.py
cacheplus/storage/redis.py
cacheplus-0.1.0.dist-info/METADATA
cacheplus-0.1.0.dist-info/WHEEL
cacheplus-0.1.0.dist-info/licenses/LICENSE
cacheplus-0.1.0.dist-info/RECORD
